Metadata-Version: 2.1
Name: github2pypi
Version: 1.0.0a0
Summary: Utils to release Python project from GitHub to PyPi.
Home-page: https://github.com/wkentaro/github2pypi
Author: Kentaro Wada
Author-email: www.kentaro.wada@gmail.com
License: MIT
Project-URL: Bug Tracker, https://github.com/wkentaro/github2pypi/issues
Keywords: "GitHub Release"
Platform: any
Classifier: Development Status :: 3 - Alpha
Classifier: Intended Audience :: Developers
Classifier: License :: OSI Approved :: MIT License
Classifier: Operating System :: OS Independent
Classifier: Programming Language :: Python
Classifier: Programming Language :: Python :: 3.4
Classifier: Programming Language :: Python :: 3.5
Classifier: Programming Language :: Python :: 3.6
Classifier: Programming Language :: Python :: 3.7
Classifier: Programming Language :: Python :: 3.8
Classifier: Topic :: Software Development :: Libraries :: Python Modules
Requires-Python: !=3.0.*,!=3.1.*,!=3.2.*,>=2.7
